pararun/__init__.py
pararun/config.py
pararun/requirements.txt
pararun/__pycache__/__init__.cpython-311.pyc
pararun/__pycache__/config.cpython-311.pyc
pararun/consumer/batcher.py
pararun/consumer/__pycache__/batcher.cpython-311.pyc
pararun/model/__init__.py
pararun/model/adapter.py
pararun/model/batcher.py
pararun/model/data_bus.py
pararun/model/status.py
pararun/model/transport_context.py
pararun/model/worker_capsule.py
pararun/model/__pycache__/__init__.cpython-311.pyc
pararun/model/__pycache__/adapter.cpython-311.pyc
pararun/model/__pycache__/batcher.cpython-311.pyc
pararun/model/__pycache__/data_bus.cpython-311.pyc
pararun/model/__pycache__/status.cpython-311.pyc
pararun/model/__pycache__/transport_context.cpython-311.pyc
pararun/model/__pycache__/worker_capsule.cpython-311.pyc
pararun/protocol/model_factory_protocol.py
pararun/protocol/queue_client_protocol.py
pararun/protocol/queue_consumer_protocol.py
pararun/protocol/queue_message_protocol.py
pararun/protocol/__pycache__/model_factory_protocol.cpython-311.pyc
pararun/protocol/__pycache__/queue_client_protocol.cpython-311.pyc
pararun/protocol/__pycache__/queue_consumer_protocol.cpython-311.pyc
pararun/protocol/__pycache__/queue_message_protocol.cpython-311.pyc
pararun/publisher/__init__.py
pararun/publisher/deferer.py
pararun/publisher/__pycache__/__init__.cpython-311.pyc
pararun/publisher/__pycache__/deferer.cpython-311.pyc
pararun/service/__init__.py
pararun/service/environment.py
pararun/service/error_handler.py
pararun/service/fallback.py
pararun/service/invokers.py
pararun/service/singleton.py
pararun/service/timed_flag.py
pararun/service/__pycache__/__init__.cpython-311.pyc
pararun/service/__pycache__/environment.cpython-311.pyc
pararun/service/__pycache__/error_handler.cpython-311.pyc
pararun/service/__pycache__/fallback.cpython-311.pyc
pararun/service/__pycache__/invokers.cpython-311.pyc
pararun/service/__pycache__/singleton.cpython-311.pyc
pararun/service/__pycache__/timed_flag.cpython-311.pyc
airembr_pararun_os-0.0.7.dist-info/METADATA
airembr_pararun_os-0.0.7.dist-info/WHEEL
airembr_pararun_os-0.0.7.dist-info/top_level.txt
airembr_pararun_os-0.0.7.dist-info/RECORD
