Metadata-Version: 2.1
Name: airembr-pararun-os
Version: 0.0.7
Summary: Airembr Pararun Module
Home-page: UNKNOWN
Author: Risto Kowaczewski
License: UNKNOWN
Keywords: airembr,sdk
Platform: UNKNOWN
Classifier: Programming Language :: Python :: 3
Classifier: License :: OSI Approved :: MIT License
Classifier: Operating System :: OS Independent
Requires-Python: >=3.10
Requires-Dist: pydantic
Requires-Dist: requests
Requires-Dist: orjson
Requires-Dist: durable-dot-dict>=0.0.22
